{
    "metadata": {
        "name": "Main Heading",
        "tooltip": "main title text",
        "type": "WIDGET",
        "icon": "text-icon"
    },
    "html": {
        "nodes": [
            {
                "element": "h1",
                "style":{
                    "text-align": {
                        "value": "",
                        "input": {
                            "type": "select",
                            "displayName": "Text Align",
                            "options": [
                                {"value": "", "text": "Default"},
                                {"value": "start", "text": "Left"},
                                {"value": "center", "text": "Center"},
                                {"value": "end", "text": "Right"}
                            ]
                        }
                    },

                    "font-family": {
                        "value":"",
                        "input":{
                            "type": "select",
                            "displayName": "Font",
                            "options":[
                                {"value": "inherit", "text": "Default"},
                                {"value": "Arial", "text": "Arial"},
                                {"value": "Verdana", "text": "Verdana"},
                                {"value": "Times New Roman", "text": "Times New Roman"},
                                {"value": "Courier New", "text": "Courier New"}
                            ]
                        }
                    },

                    "font-size": {
                        "value":"",
                        "input":{
                            "type": "select",
                            "displayName": "Font Size",
                            "options":[
                                {"value": "", "text": "Default"},
                                {"value": ".5rem", "text": "Very Small"},
                                {"value": ".8rem", "text": "Small"},
                                {"value": "1.1rem", "text": "Medium"},
                                {"value": "1.5rem", "text": "Large"},
                                {"value": "1.8rem", "text": "Very Large"}
                            ]
                        }
                    },

                    "font-weight": {
                        "value":"",
                        "input":{
                            "type": "select",
                            "displayName": "Font Weight",
                            "options":[
                                {"value": "", "text": "Default"},
                                {"value": "50", "text": "Lighter"},
                                {"value": "100", "text": "Light"},
                                {"value": "200", "text": "Normal"},
                                {"value": "400", "text": "Bold"},
                                {"value": "600", "text": "Bolder"}
                            ]
                        }
                    },
                    "color":{
                        "value": "",
                        "input": {
                            "type": "color",
                            "displayName": "Text Color"
                        }
                    }
                },
                "attributes":{
                    "text": {
                        "value": "Main Heading",
                        "suppress": true,
                        "input": {
                            "type": "text"
                        }
                    },
                    "className": {
                        "value": "heading1",
                        "readonly": true,
                        "input": {
                            "type": "text"
                        }
                    }
                },
                "children": [],
                "metadata":{
                    "draggable": true,
                    "childDirection": "vertical",
                    "selectable": true
                }
            }
        ]
    }
}